wrapper_test/__init__.py
wrapper_test/_wrapper_test.cp312-win_amd64.pyd
wrapper_test/wrapper_test.py
wrapper_test-0.0.3.dist-info/METADATA
wrapper_test-0.0.3.dist-info/WHEEL
wrapper_test-0.0.3.dist-info/RECORD
