Metadata-Version: 2.1
Name: wrapper_test
Version: 0.0.3
Summary: Wrapper Test
Author: Erasmo
Author-email: erasmo.pe@gmail.com
Requires-Python: >=3.8,<4.0
Classifier: Programming Language :: Python :: 3
Classifier: Programming Language :: Python :: 3.8
Classifier: Programming Language :: Python :: 3.9
Classifier: Programming Language :: Python :: 3.10
Classifier: Programming Language :: Python :: 3.11
Classifier: Programming Language :: Python :: 3.12
